odoo/addons/pos_picking_load_partner_name/README.rst
odoo/addons/pos_picking_load_partner_name/__init__.py
odoo/addons/pos_picking_load_partner_name/__manifest__.py
odoo/addons/pos_picking_load_partner_name/hooks.py
odoo/addons/pos_picking_load_partner_name/i18n/es.po
odoo/addons/pos_picking_load_partner_name/i18n/fr.po
odoo/addons/pos_picking_load_partner_name/i18n/pos_picking_load_partner_name.pot
odoo/addons/pos_picking_load_partner_name/models/__init__.py
odoo/addons/pos_picking_load_partner_name/models/stock_picking.py
odoo/addons/pos_picking_load_partner_name/readme/CONTRIBUTORS.rst
odoo/addons/pos_picking_load_partner_name/readme/DESCRIPTION.rst
odoo/addons/pos_picking_load_partner_name/static/description/icon.png
odoo/addons/pos_picking_load_partner_name/static/description/index.html
odoo12_addon_pos_picking_load_partner_name-12.0.1.0.2.dist-info/METADATA
odoo12_addon_pos_picking_load_partner_name-12.0.1.0.2.dist-info/WHEEL
odoo12_addon_pos_picking_load_partner_name-12.0.1.0.2.dist-info/top_level.txt
odoo12_addon_pos_picking_load_partner_name-12.0.1.0.2.dist-info/RECORD
